alibabacloud_hbr20170908/__init__.py
alibabacloud_hbr20170908/client.py
alibabacloud_hbr20170908/models/__init__.py
alibabacloud_hbr20170908/models/_add_container_cluster_request.py
alibabacloud_hbr20170908/models/_add_container_cluster_response.py
alibabacloud_hbr20170908/models/_add_container_cluster_response_body.py
alibabacloud_hbr20170908/models/_add_cross_account_request.py
alibabacloud_hbr20170908/models/_add_cross_account_response.py
alibabacloud_hbr20170908/models/_add_cross_account_response_body.py
alibabacloud_hbr20170908/models/_cancel_backup_job_request.py
alibabacloud_hbr20170908/models/_cancel_backup_job_response.py
alibabacloud_hbr20170908/models/_cancel_backup_job_response_body.py
alibabacloud_hbr20170908/models/_cancel_restore_job_request.py
alibabacloud_hbr20170908/models/_cancel_restore_job_response.py
alibabacloud_hbr20170908/models/_cancel_restore_job_response_body.py
alibabacloud_hbr20170908/models/_change_resource_group_request.py
alibabacloud_hbr20170908/models/_change_resource_group_response.py
alibabacloud_hbr20170908/models/_change_resource_group_response_body.py
alibabacloud_hbr20170908/models/_check_role_request.py
alibabacloud_hbr20170908/models/_check_role_response.py
alibabacloud_hbr20170908/models/_check_role_response_body.py
alibabacloud_hbr20170908/models/_create_backup_job_request.py
alibabacloud_hbr20170908/models/_create_backup_job_response.py
alibabacloud_hbr20170908/models/_create_backup_job_response_body.py
alibabacloud_hbr20170908/models/_create_backup_job_shrink_request.py
alibabacloud_hbr20170908/models/_create_backup_plan_request.py
alibabacloud_hbr20170908/models/_create_backup_plan_response.py
alibabacloud_hbr20170908/models/_create_backup_plan_response_body.py
alibabacloud_hbr20170908/models/_create_backup_plan_shrink_request.py
alibabacloud_hbr20170908/models/_create_clients_request.py
alibabacloud_hbr20170908/models/_create_clients_response.py
alibabacloud_hbr20170908/models/_create_clients_response_body.py
alibabacloud_hbr20170908-2.4.0.dist-info/LICENSE
alibabacloud_hbr20170908-2.4.0.dist-info/METADATA
alibabacloud_hbr20170908-2.4.0.dist-info/WHEEL
alibabacloud_hbr20170908-2.4.0.dist-info/top_level.txt
alibabacloud_hbr20170908-2.4.0.dist-info/RECORD
